[{"Season": 2023, "SeasonType": 1, "TeamID": 9, "Key": "BOS", "City": "Boston", "Name": "Celtics", "Conference": "Eastern", "Division": "Atlantic", "Wins": 18, "Losses": 4, "Percentage": 0.818, "ConferenceWins": 12, "ConferenceLosses": 4, "DivisionWins": 2, "DivisionLosses": 0, "HomeWins": 11, "HomeLosses": 1, "AwayWins": 7, "AwayLosses": 3, "LastTenWins": 9, "LastTenLosses": 1, "PointsPerGameFor": 121.86, "PointsPerGameAgainst": 113.27, "Streak": 5, "GamesBack": 0.0, "StreakDescription": "W5", "GlobalTeamID": 20000009, "ConferenceRank": 1, "DivisionRank": 1}, {"Season": 2023, "SeasonType": 1, "TeamID": 7, "Key": "PHI", "City": "Philadelphia", "Name": "76ers", "Conference": "Eastern", "Division": "Atlantic", "Wins": 12, "Losses": 10, "Percentage": 0.545, "ConferenceWins": 10, "ConferenceLosses": 8, "DivisionWins": 2, "DivisionLosses": 3, "HomeWins": 7, "HomeLosses": 5, "AwayWins": 5, "AwayLosses": 5, "LastTenWins": 7, "LastTenLosses": 3, "PointsPerGameFor": 108.31, "PointsPerGameAgainst": 106.09, "Streak": -1, "GamesBack": 6.0, "StreakDescription": "L1", "GlobalTeamID": 20000007, "ConferenceRank": 4, "DivisionRank": 2}, {"Season": 2023, "SeasonType": 1, "TeamID": 10, "Key": "TOR", "City": "Toronto", "Name": "Raptors", "Conference": "Eastern", "Division": "Atlantic", "Wins": 11, "Losses": 10, "Percentage": 0.524, "ConferenceWins": 8, "ConferenceLosses": 7, "DivisionWins": 1, "DivisionLosses": 3, "HomeWins": 8, "HomeLosses": 2, "AwayWins": 3, "AwayLosses": 8, "LastTenWins": 5, "LastTenLosses": 5, "PointsPerGameFor": 110.66, "PointsPerGameAgainst": 109.33, "Streak": -1, "GamesBack": 6.5, "StreakDescription": "L1", "GlobalTeamID": 20000010, "ConferenceRank": 6, "DivisionRank": 3}, {"Season": 2023, "SeasonType": 1, "TeamID": 8, "Key": "BKN", "City": "Brooklyn", "Name": "Nets", "Conference": "Eastern", "Division": "Atlantic", "Wins": 12, "Losses": 11, "Percentage": 0.522, "ConferenceWins": 8, "ConferenceLosses": 5, "DivisionWins": 3, "DivisionLosses": 1, "HomeWins": 7, "HomeLosses": 4, "AwayWins": 5, "AwayLosses": 7, "LastTenWins": 6, "LastTenLosses": 4, "PointsPerGameFor": 111.56, "PointsPerGameAgainst": 110.6, "Streak": 3, "GamesBack": 6.5, "StreakDescription": "W3", "GlobalTeamID": 20000008, "ConferenceRank": 7, "DivisionRank": 4}, {"Season": 2023, "SeasonType": 1, "TeamID": 6, "Key": "NY", "City": "New York", "Name": "Knicks", "Conference": "Eastern", "Division": "Atlantic", "Wins": 10, "Losses": 12, "Percentage": 0.455, "ConferenceWins": 6, "ConferenceLosses": 6, "DivisionWins": 1, "DivisionLosses": 2, "HomeWins": 4, "HomeLosses": 6, "AwayWins": 6, "AwayLosses": 6, "LastTenWins": 4, "LastTenLosses": 6, "PointsPerGameFor": 115.22, "PointsPerGameAgainst": 116.22, "Streak": -1, "GamesBack": 8.0, "StreakDescription": "L1", "GlobalTeamID": 20000006, "ConferenceRank": 9, "DivisionRank": 4}, {"Season": 2023, "SeasonType": 1, "TeamID": 15, "Key": "MIL", "City": "Milwaukee", "Name": "Bucks", "Conference": "Eastern", "Division": "Central", "Wins": 15, "Losses": 5, "Percentage": 0.75, "ConferenceWins": 9, "ConferenceLosses": 4, "DivisionWins": 4, "DivisionLosses": 1, "HomeWins": 11, "HomeLosses": 2, "AwayWins": 4, "AwayLosses": 3, "LastTenWins": 6, "LastTenLosses": 4, "PointsPerGameFor": 112.3, "PointsPerGameAgainst": 107.4, "Streak": 3, "GamesBack": 2.0, "StreakDescription": "W3", "GlobalTeamID": 20000015, "ConferenceRank": 2, "DivisionRank": 1}, {"Season": 2023, "SeasonType": 1, "TeamID": 12, "Key": "CLE", "City": "Cleveland", "Name": "Cavaliers", "Conference": "Eastern", "Division": "Central", "Wins": 14, "Losses": 8, "Percentage": 0.636, "ConferenceWins": 12, "ConferenceLosses": 4, "DivisionWins": 3, "DivisionLosses": 2, "HomeWins": 9, "HomeLosses": 1, "AwayWins": 5, "AwayLosses": 7, "LastTenWins": 6, "LastTenLosses": 4, "PointsPerGameFor": 112.9, "PointsPerGameAgainst": 106.0, "Streak": 1, "GamesBack": 4.0, "StreakDescription": "W1", "GlobalTeamID": 20000012, "ConferenceRank": 3, "DivisionRank": 2}, {"Season": 2023, "SeasonType": 1, "TeamID": 13, "Key": "IND", "City": "Indiana", "Name": "Pacers", "Conference": "Eastern", "Division": "Central", "Wins": 12, "Losses": 9, "Percentage": 0.571, "ConferenceWins": 9, "ConferenceLosses": 4, "DivisionWins": 1, "DivisionLosses": 1, "HomeWins": 7, "HomeLosses": 4, "AwayWins": 5, "AwayLosses": 5, "LastTenWins": 7, "LastTenLosses": 3, "PointsPerGameFor": 115.61, "PointsPerGameAgainst": 115.38, "Streak": -1, "GamesBack": 5.5, "StreakDescription": "L1", "GlobalTeamID": 20000013, "ConferenceRank": 4, "DivisionRank": 3}, {"Season": 2023, "SeasonType": 1, "TeamID": 11, "Key": "CHI", "City": "Chicago", "Name": "Bulls", "Conference": "Eastern", "Division": "Central", "Wins": 9, "Losses": 12, "Percentage": 0.429, "ConferenceWins": 8, "ConferenceLosses": 6, "DivisionWins": 2, "DivisionLosses": 1, "HomeWins": 5, "HomeLosses": 5, "AwayWins": 4, "AwayLosses": 7, "LastTenWins": 4, "LastTenLosses": 6, "PointsPerGameFor": 112.04, "PointsPerGameAgainst": 112.71, "Streak": -1, "GamesBack": 8.5, "StreakDescription": "L1", "GlobalTeamID": 20000011, "ConferenceRank": 11, "DivisionRank": 4}, {"Season": 2023, "SeasonType": 1, "TeamID": 14, "Key": "DET", "City": "Detroit", "Name": "Pistons", "Conference": "Eastern", "Division": "Central", "Wins": 5, "Losses": 18, "Percentage": 0.217, "ConferenceWins": 1, "ConferenceLosses": 14, "DivisionWins": 0, "DivisionLosses": 5, "HomeWins": 3, "HomeLosses": 7, "AwayWins": 2, "AwayLosses": 11, "LastTenWins": 2, "LastTenLosses": 8, "PointsPerGameFor": 109.13, "PointsPerGameAgainst": 117.73, "Streak": -3, "GamesBack": 13.5, "StreakDescription": "L3", "GlobalTeamID": 20000014, "ConferenceRank": 14, "DivisionRank": 4}, {"Season": 2023, "SeasonType": 1, "TeamID": 3, "Key": "ATL", "City": "Atlanta", "Name": "Hawks", "Conference": "Eastern", "Division": "Southeast", "Wins": 12, "Losses": 10, "Percentage": 0.545, "ConferenceWins": 9, "ConferenceLosses": 8, "DivisionWins": 2, "DivisionLosses": 2, "HomeWins": 7, "HomeLosses": 4, "AwayWins": 5, "AwayLosses": 6, "LastTenWins": 4, "LastTenLosses": 6, "PointsPerGameFor": 113.9, "PointsPerGameAgainst": 113.5, "Streak": 1, "GamesBack": 6.0, "StreakDescription": "W1", "GlobalTeamID": 20000003, "ConferenceRank": 5, "DivisionRank": 1}, {"Season": 2023, "SeasonType": 1, "TeamID": 1, "Key": "WAS", "City": "Washington", "Name": "Wizards", "Conference": "Eastern", "Division": "Southeast", "Wins": 11, "Losses": 11, "Percentage": 0.5, "ConferenceWins": 7, "ConferenceLosses": 9, "DivisionWins": 3, "DivisionLosses": 2, "HomeWins": 8, "HomeLosses": 4, "AwayWins": 3, "AwayLosses": 7, "LastTenWins": 5, "LastTenLosses": 5, "PointsPerGameFor": 110.36, "PointsPerGameAgainst": 111.5, "Streak": -1, "GamesBack": 7.0, "StreakDescription": "L1", "GlobalTeamID": 20000001, "ConferenceRank": 8, "DivisionRank": 2}, {"Season": 2023, "SeasonType": 1, "TeamID": 4, "Key": "MIA", "City": "Miami", "Name": "Heat", "Conference": "Eastern", "Division": "Southeast", "Wins": 10, "Losses": 12, "Percentage": 0.455, "ConferenceWins": 6, "ConferenceLosses": 8, "DivisionWins": 5, "DivisionLosses": 1, "HomeWins": 8, "HomeLosses": 4, "AwayWins": 2, "AwayLosses": 8, "LastTenWins": 5, "LastTenLosses": 5, "PointsPerGameFor": 109.0, "PointsPerGameAgainst": 110.04, "Streak": -1, "GamesBack": 8.0, "StreakDescription": "L1", "GlobalTeamID": 20000004, "ConferenceRank": 10, "DivisionRank": 3}, {"Season": 2023, "SeasonType": 1, "TeamID": 2, "Key": "CHA", "City": "Charlotte", "Name": "Hornets", "Conference": "Eastern", "Division": "Southeast", "Wins": 6, "Losses": 15, "Percentage": 0.286, "ConferenceWins": 3, "ConferenceLosses": 11, "DivisionWins": 2, "DivisionLosses": 5, "HomeWins": 3, "HomeLosses": 6, "AwayWins": 3, "AwayLosses": 9, "LastTenWins": 3, "LastTenLosses": 7, "PointsPerGameFor": 109.19, "PointsPerGameAgainst": 115.38, "Streak": -1, "GamesBack": 11.5, "StreakDescription": "L1", "GlobalTeamID": 20000002, "ConferenceRank": 12, "DivisionRank": 4}, {"Season": 2023, "SeasonType": 1, "TeamID": 5, "Key": "ORL", "City": "Orlando", "Name": "Magic", "Conference": "Eastern", "Division": "Southeast", "Wins": 5, "Losses": 17, "Percentage": 0.227, "ConferenceWins": 2, "ConferenceLosses": 12, "DivisionWins": 1, "DivisionLosses": 3, "HomeWins": 4, "HomeLosses": 8, "AwayWins": 1, "AwayLosses": 9, "LastTenWins": 2, "LastTenLosses": 8, "PointsPerGameFor": 108.31, "PointsPerGameAgainst": 114.4, "Streak": -6, "GamesBack": 13.0, "StreakDescription": "L6", "GlobalTeamID": 20000005, "ConferenceRank": 13, "DivisionRank": 4}, {"Season": 2023, "SeasonType": 1, "TeamID": 20, "Key": "DEN", "City": "Denver", "Name": "Nuggets", "Conference": "Western", "Division": "Northwest", "Wins": 14, "Losses": 7, "Percentage": 0.667, "ConferenceWins": 12, "ConferenceLosses": 4, "DivisionWins": 4, "DivisionLosses": 2, "HomeWins": 6, "HomeLosses": 2, "AwayWins": 8, "AwayLosses": 5, "LastTenWins": 6, "LastTenLosses": 4, "PointsPerGameFor": 115.42, "PointsPerGameAgainst": 113.09, "Streak": 4, "GamesBack": 1.0, "StreakDescription": "W4", "GlobalTeamID": 20000020, "ConferenceRank": 2, "DivisionRank": 1}, {"Season": 2023, "SeasonType": 1, "TeamID": 17, "Key": "UTA", "City": "Utah", "Name": "Jazz", "Conference": "Western", "Division": "Northwest", "Wins": 13, "Losses": 11, "Percentage": 0.542, "ConferenceWins": 12, "ConferenceLosses": 6, "DivisionWins": 3, "DivisionLosses": 1, "HomeWins": 7, "HomeLosses": 3, "AwayWins": 6, "AwayLosses": 8, "LastTenWins": 3, "LastTenLosses": 7, "PointsPerGameFor": 117.04, "PointsPerGameAgainst": 115.37, "Streak": 1, "GamesBack": 3.5, "StreakDescription": "W1", "GlobalTeamID": 20000017, "ConferenceRank": 6, "DivisionRank": 2}, {"Season": 2023, "SeasonType": 1, "TeamID": 16, "Key": "MIN", "City": "Minnesota", "Name": "Timberwolves", "Conference": "Western", "Division": "Northwest", "Wins": 11, "Losses": 11, "Percentage": 0.5, "ConferenceWins": 6, "ConferenceLosses": 7, "DivisionWins": 2, "DivisionLosses": 1, "HomeWins": 6, "HomeLosses": 6, "AwayWins": 5, "AwayLosses": 5, "LastTenWins": 6, "LastTenLosses": 4, "PointsPerGameFor": 114.36, "PointsPerGameAgainst": 115.27, "Streak": 1, "GamesBack": 4.5, "StreakDescription": "W1", "GlobalTeamID": 20000016, "ConferenceRank": 8, "DivisionRank": 3}, {"Season": 2023, "SeasonType": 1, "TeamID": 19, "Key": "POR", "City": "Portland", "Name": "Trail Blazers", "Conference": "Western", "Division": "Northwest", "Wins": 11, "Losses": 11, "Percentage": 0.5, "ConferenceWins": 8, "ConferenceLosses": 6, "DivisionWins": 1, "DivisionLosses": 1, "HomeWins": 4, "HomeLosses": 5, "AwayWins": 7, "AwayLosses": 6, "LastTenWins": 2, "LastTenLosses": 8, "PointsPerGameFor": 109.77, "PointsPerGameAgainst": 111.45, "Streak": -3, "GamesBack": 4.5, "StreakDescription": "L3", "GlobalTeamID": 20000019, "ConferenceRank": 9, "DivisionRank": 4}, {"Season": 2023, "SeasonType": 1, "TeamID": 18, "Key": "OKC", "City": "Oklahoma City", "Name": "Thunder", "Conference": "Western", "Division": "Northwest", "Wins": 9, "Losses": 13, "Percentage": 0.409, "ConferenceWins": 4, "ConferenceLosses": 8, "DivisionWins": 0, "DivisionLosses": 5, "HomeWins": 6, "HomeLosses": 5, "AwayWins": 3, "AwayLosses": 8, "LastTenWins": 4, "LastTenLosses": 6, "PointsPerGameFor": 116.0, "PointsPerGameAgainst": 117.36, "Streak": 1, "GamesBack": 6.5, "StreakDescription": "W1", "GlobalTeamID": 20000018, "ConferenceRank": 11, "DivisionRank": 4}, {"Season": 2023, "SeasonType": 1, "TeamID": 29, "Key": "PHO", "City": "Phoenix", "Name": "Suns", "Conference": "Western", "Division": "Pacific", "Wins": 15, "Losses": 6, "Percentage": 0.714, "ConferenceWins": 12, "ConferenceLosses": 3, "DivisionWins": 5, "DivisionLosses": 0, "HomeWins": 12, "HomeLosses": 1, "AwayWins": 3, "AwayLosses": 5, "LastTenWins": 7, "LastTenLosses": 3, "PointsPerGameFor": 115.76, "PointsPerGameAgainst": 108.38, "Streak": 6, "GamesBack": 0.0, "StreakDescription": "W6", "GlobalTeamID": 20000029, "ConferenceRank": 1, "DivisionRank": 1}, {"Season": 2023, "SeasonType": 1, "TeamID": 28, "Key": "LAC", "City": "Los Angeles", "Name": "Clippers", "Conference": "Western", "Division": "Pacific", "Wins": 13, "Losses": 10, "Percentage": 0.565, "ConferenceWins": 10, "ConferenceLosses": 9, "DivisionWins": 3, "DivisionLosses": 2, "HomeWins": 7, "HomeLosses": 5, "AwayWins": 6, "AwayLosses": 5, "LastTenWins": 6, "LastTenLosses": 4, "PointsPerGameFor": 107.17, "PointsPerGameAgainst": 107.82, "Streak": -1, "GamesBack": 3.0, "StreakDescription": "L1", "GlobalTeamID": 20000028, "ConferenceRank": 4, "DivisionRank": 2}, {"Season": 2023, "SeasonType": 1, "TeamID": 30, "Key": "SAC", "City": "Sacramento", "Name": "Kings", "Conference": "Western", "Division": "Pacific", "Wins": 11, "Losses": 9, "Percentage": 0.55, "ConferenceWins": 4, "ConferenceLosses": 6, "DivisionWins": 2, "DivisionLosses": 4, "HomeWins": 7, "HomeLosses": 4, "AwayWins": 4, "AwayLosses": 5, "LastTenWins": 7, "LastTenLosses": 3, "PointsPerGameFor": 119.9, "PointsPerGameAgainst": 117.2, "Streak": 1, "GamesBack": 3.5, "StreakDescription": "W1", "GlobalTeamID": 20000030, "ConferenceRank": 5, "DivisionRank": 3}, {"Season": 2023, "SeasonType": 1, "TeamID": 26, "Key": "GS", "City": "Golden State", "Name": "Warriors", "Conference": "Western", "Division": "Pacific", "Wins": 11, "Losses": 11, "Percentage": 0.5, "ConferenceWins": 8, "ConferenceLosses": 7, "DivisionWins": 4, "DivisionLosses": 3, "HomeWins": 9, "HomeLosses": 1, "AwayWins": 2, "AwayLosses": 10, "LastTenWins": 6, "LastTenLosses": 4, "PointsPerGameFor": 117.54, "PointsPerGameAgainst": 117.22, "Streak": -1, "GamesBack": 4.5, "StreakDescription": "L1", "GlobalTeamID": 20000026, "ConferenceRank": 7, "DivisionRank": 4}, {"Season": 2023, "SeasonType": 1, "TeamID": 27, "Key": "LAL", "City": "Los Angeles", "Name": "Lakers", "Conference": "Western", "Division": "Pacific", "Wins": 8, "Losses": 12, "Percentage": 0.4, "ConferenceWins": 6, "ConferenceLosses": 10, "DivisionWins": 0, "DivisionLosses": 5, "HomeWins": 6, "HomeLosses": 6, "AwayWins": 2, "AwayLosses": 6, "LastTenWins": 6, "LastTenLosses": 4, "PointsPerGameFor": 113.1, "PointsPerGameAgainst": 114.25, "Streak": 1, "GamesBack": 6.5, "StreakDescription": "W1", "GlobalTeamID": 20000027, "ConferenceRank": 12, "DivisionRank": 4}, {"Season": 2023, "SeasonType": 1, "TeamID": 23, "Key": "NO", "City": "New Orleans", "Name": "Pelicans", "Conference": "Western", "Division": "Southwest", "Wins": 13, "Losses": 8, "Percentage": 0.619, "ConferenceWins": 8, "ConferenceLosses": 5, "DivisionWins": 4, "DivisionLosses": 1, "HomeWins": 8, "HomeLosses": 3, "AwayWins": 5, "AwayLosses": 5, "LastTenWins": 7, "LastTenLosses": 3, "PointsPerGameFor": 117.09, "PointsPerGameAgainst": 111.04, "Streak": 2, "GamesBack": 2.0, "StreakDescription": "W2", "GlobalTeamID": 20000023, "ConferenceRank": 3, "DivisionRank": 1}, {"Season": 2023, "SeasonType": 1, "TeamID": 21, "Key": "MEM", "City": "Memphis", "Name": "Grizzlies", "Conference": "Western", "Division": "Southwest", "Wins": 12, "Losses": 9, "Percentage": 0.571, "ConferenceWins": 7, "ConferenceLosses": 6, "DivisionWins": 3, "DivisionLosses": 2, "HomeWins": 7, "HomeLosses": 2, "AwayWins": 5, "AwayLosses": 7, "LastTenWins": 5, "LastTenLosses": 5, "PointsPerGameFor": 114.95, "PointsPerGameAgainst": 114.0, "Streak": -1, "GamesBack": 3.0, "StreakDescription": "L1", "GlobalTeamID": 20000021, "ConferenceRank": 4, "DivisionRank": 2}, {"Season": 2023, "SeasonType": 1, "TeamID": 25, "Key": "DAL", "City": "Dallas", "Name": "Mavericks", "Conference": "Western", "Division": "Southwest", "Wins": 10, "Losses": 10, "Percentage": 0.5, "ConferenceWins": 6, "ConferenceLosses": 5, "DivisionWins": 1, "DivisionLosses": 2, "HomeWins": 9, "HomeLosses": 3, "AwayWins": 1, "AwayLosses": 7, "LastTenWins": 4, "LastTenLosses": 6, "PointsPerGameFor": 109.4, "PointsPerGameAgainst": 107.6, "Streak": 1, "GamesBack": 4.5, "StreakDescription": "W1", "GlobalTeamID": 20000025, "ConferenceRank": 10, "DivisionRank": 3}, {"Season": 2023, "SeasonType": 1, "TeamID": 24, "Key": "SA", "City": "San Antonio", "Name": "Spurs", "Conference": "Western", "Division": "Southwest", "Wins": 6, "Losses": 16, "Percentage": 0.273, "ConferenceWins": 2, "ConferenceLosses": 14, "DivisionWins": 0, "DivisionLosses": 2, "HomeWins": 3, "HomeLosses": 8, "AwayWins": 3, "AwayLosses": 8, "LastTenWins": 1, "LastTenLosses": 9, "PointsPerGameFor": 110.63, "PointsPerGameAgainst": 120.95, "Streak": -9, "GamesBack": 9.5, "StreakDescription": "L9", "GlobalTeamID": 20000024, "ConferenceRank": 13, "DivisionRank": 4}, {"Season": 2023, "SeasonType": 1, "TeamID": 22, "Key": "HOU", "City": "Houston", "Name": "Rockets", "Conference": "Western", "Division": "Southwest", "Wins": 5, "Losses": 16, "Percentage": 0.238, "ConferenceWins": 3, "ConferenceLosses": 12, "DivisionWins": 1, "DivisionLosses": 2, "HomeWins": 3, "HomeLosses": 5, "AwayWins": 2, "AwayLosses": 11, "LastTenWins": 3, "LastTenLosses": 7, "PointsPerGameFor": 109.8, "PointsPerGameAgainst": 116.57, "Streak": -2, "GamesBack": 10.0, "StreakDescription": "L2", "GlobalTeamID": 20000022, "ConferenceRank": 14, "DivisionRank": 4}]